libyaml_vendor/_dummy.cpython-310-x86_64-linux-gnu.so
ros_libyaml_vendor-1.7.1.data/data/share/ament_index/resource_index/package_run_dependencies/libyaml_vendor
ros_libyaml_vendor-1.7.1.data/data/share/ament_index/resource_index/packages/libyaml_vendor
ros_libyaml_vendor-1.7.1.data/data/share/ament_index/resource_index/parent_prefix_path/libyaml_vendor
ros_libyaml_vendor-1.7.1.data/data/share/libyaml_vendor/local_setup.bash
ros_libyaml_vendor-1.7.1.data/data/share/libyaml_vendor/local_setup.dsv
ros_libyaml_vendor-1.7.1.data/data/share/libyaml_vendor/local_setup.sh
ros_libyaml_vendor-1.7.1.data/data/share/libyaml_vendor/local_setup.zsh
ros_libyaml_vendor-1.7.1.data/data/share/libyaml_vendor/package.dsv
ros_libyaml_vendor-1.7.1.data/data/share/libyaml_vendor/package.xml
ros_libyaml_vendor-1.7.1.data/data/share/libyaml_vendor/cmake/ament_cmake_export_dependencies-extras.cmake
ros_libyaml_vendor-1.7.1.data/data/share/libyaml_vendor/cmake/libyaml_vendor-extras.cmake
ros_libyaml_vendor-1.7.1.data/data/share/libyaml_vendor/cmake/libyaml_vendorConfig-version.cmake
ros_libyaml_vendor-1.7.1.data/data/share/libyaml_vendor/cmake/libyaml_vendorConfig.cmake
ros_libyaml_vendor-1.7.1.data/data/share/libyaml_vendor/cmake/Modules/Findyaml.cmake
ros_libyaml_vendor-1.7.1.data/data/share/libyaml_vendor/environment/ament_prefix_path.dsv
ros_libyaml_vendor-1.7.1.data/data/share/libyaml_vendor/environment/ament_prefix_path.sh
ros_libyaml_vendor-1.7.1.data/data/share/libyaml_vendor/environment/path.dsv
ros_libyaml_vendor-1.7.1.data/data/share/libyaml_vendor/environment/path.sh
ros_libyaml_vendor-1.7.1.dist-info/METADATA
ros_libyaml_vendor-1.7.1.dist-info/WHEEL
ros_libyaml_vendor-1.7.1.dist-info/top_level.txt
ros_libyaml_vendor-1.7.1.dist-info/RECORD
ros_libyaml_vendor-1.7.1.dist-info/licenses/LICENSE
