Metadata-Version: 2.4
Name: ros-libyaml-vendor
Version: 1.7.1
Summary: A ROS package providing a CMake wrapper to ensure the ROS 2-compatible libyaml library is available for other projects.
License-File: LICENSE
Dynamic: description
Dynamic: description-content-type
Dynamic: license-file
Dynamic: summary
